tricolour/__init__.py
tricolour/apps/__init__.py
tricolour/apps/tricolour/__init__.py
tricolour/apps/tricolour/app.py
tricolour/apps/tricolour/strat_executor.py
tricolour/banner.py
tricolour/conf/default.yaml
tricolour/dask_wrappers.py
tricolour/data/4k_lband_meerkat.staticmask
tricolour/data/4k_uhfband_meerkat.staticmask
tricolour/flagging.py
tricolour/mask.py
tricolour/packing.py
tricolour/post_mortem_handler.py
tricolour/stokes.py
tricolour/tests/custom.yaml
tricolour/tests/test_acceptance.py
tricolour/tests/test_flagging.py
tricolour/tests/test_flagging_additional.py
tricolour/tests/test_packing.py
tricolour/tests/test_stokes.py
tricolour/tests/test_window_statistics.py
tricolour/util.py
tricolour/window_statistics.py
tricolour-0.2.0.dist-info/METADATA
tricolour-0.2.0.dist-info/WHEEL
tricolour-0.2.0.dist-info/entry_points.txt
tricolour-0.2.0.dist-info/licenses/AUTHORS.rst
tricolour-0.2.0.dist-info/licenses/LICENSE
tricolour-0.2.0.dist-info/RECORD
