Metadata-Version: 2.4
Name: tricolour
Version: 0.2.0
Summary: Science Data Processing flagging code, wrapped in dask
License: GPLv2
License-File: AUTHORS.rst
License-File: LICENSE
Author: Simon Perkins
Requires-Python: >=3.10,<3.13
Classifier: License :: Other/Proprietary License
Classifier: Programming Language :: Python :: 3
Classifier: Programming Language :: Python :: 3.10
Classifier: Programming Language :: Python :: 3.11
Classifier: Programming Language :: Python :: 3.12
Provides-Extra: testing
Requires-Dist: dask-ms (>=0.2.23,<0.3.0)
Requires-Dist: donfig (>=0.8.1.post1,<0.9.0)
Requires-Dist: numba (>=0.60.0,<0.61.0)
Requires-Dist: numpy (>2.0)
Requires-Dist: scipy (>1.9.0)
Requires-Dist: threadpoolctl (>=3.5.0,<4.0.0)
Requires-Dist: zarr (>=2.18.3,<3.0.0)
